cartogram/__init__.py
cartogram/_constants.py
cartogram/_utils.py
cartogram/dorling.py
cartogram/dorling_compress.py
cartogram_nuuuwan-1.0.0.dist-info/LICENSE
cartogram_nuuuwan-1.0.0.dist-info/METADATA
cartogram_nuuuwan-1.0.0.dist-info/WHEEL
cartogram_nuuuwan-1.0.0.dist-info/top_level.txt
cartogram_nuuuwan-1.0.0.dist-info/RECORD
