Metadata-Version: 2.1
Name: cartogram-nuuuwan
Version: 1.0.0
Summary: UNKNOWN
Home-page: https://github.com/nuuuwan/cartogram
Author: Nuwan I. Senaratna
Author-email: nuuuwan@gmail.com
License: UNKNOWN
Project-URL: Bug Tracker, https://github.com/nuuuwan/cartogram/issues
Platform: UNKNOWN
Classifier: Programming Language :: Python :: 3
Classifier: License :: OSI Approved :: MIT License
Classifier: Operating System :: OS Independent
Requires-Python: >=3.6
License-File: LICENSE
Requires-Dist: utils-nuuuwan
Requires-Dist: matplotlib
